graphone/__init__.py
graphone/cli/__init__.py
graphone/cli/main.py
graphone/documents/__init__.py
graphone/documents/markdown/__init__.py
graphone/documents/markdown/cleaner/README.md
graphone/documents/markdown/cleaner/__init__.py
graphone/documents/markdown/cleaner/config.py
graphone/documents/markdown/cleaner/handlers.py
graphone/documents/markdown/cleaner/markdown_cleaner.py
graphone/documents/markdown/cleaner/strategies.py
graphone/documents/markdown/cleaner/tests/ast_debug.json
graphone/documents/markdown/cleaner/tests/test.py
graphone/documents/markdown/cleaner/tests/test_document.md
graphone/tui/__init__.py
graphone/tui/config.py
graphone/tui/main.py
graphone/tui/screens/__init__.py
graphone/tui/screens/configurator.py
graphone/tui/screens/modals.py
graphone/tui/utils/__init__.py
graphone/tui/utils/styles.py
graphone/tui/widgets/__init__.py
graphone/tui/widgets/sidebar.py
graphone-0.0.1.dist-info/licenses/LICENSE
graphone-0.0.1.dist-info/METADATA
graphone-0.0.1.dist-info/WHEEL
graphone-0.0.1.dist-info/entry_points.txt
graphone-0.0.1.dist-info/top_level.txt
graphone-0.0.1.dist-info/RECORD
