Metadata-Version: 2.4
Name: graphone
Version: 0.0.1
Summary: Node management and control system for swarm infrastructure.
Author-email: Don Valerio <iam@donvalerio.com>
License: MIT
Project-URL: Homepage, https://agent.donvalerio.com
Project-URL: Documentation, https://github.com/GraphEn-One/swarm/tree/master/docs/graphone/
Project-URL: Repository, https://github.com/GraphEn-One/swarm
Project-URL: Issues, https://github.com/GraphEn-One/swarm/issues
Keywords: node,management,control,swarm,tui,cli
Classifier: Development Status :: 3 - Alpha
Classifier: Intended Audience :: Developers
Classifier: License :: OSI Approved :: MIT License
Classifier: Programming Language :: Python :: 3.10
Classifier: Programming Language :: Python :: 3.11
Classifier: Programming Language :: Python :: 3.12
Classifier: Programming Language :: Python :: 3.13
Classifier: Topic :: Software Development :: Libraries :: Python Modules
Classifier: Topic :: System :: Monitoring
Requires-Python: >=3.10
License-File: LICENSE
Provides-Extra: tui
Requires-Dist: textual>=7.5.0; extra == "tui"
Provides-Extra: dev
Requires-Dist: pytest>=7.0.0; extra == "dev"
Requires-Dist: black>=23.0.0; extra == "dev"
Requires-Dist: mypy>=1.0.0; extra == "dev"
Dynamic: license-file
